qtlottie/__init__.py
qtlottie/compat.py
qtlottie/py.typed
qtlottie/core/__init__.py
qtlottie/core/animation.py
qtlottie/core/cache.py
qtlottie/core/controller.py
qtlottie/qml/__init__.py
qtlottie/qml/register.py
qtlottie/rlottie/__init__.py
qtlottie/rlottie/wrapper.py
qtlottie/utils/__init__.py
qtlottie/utils/math.py
qt_lottie-0.1.3.dist-info/METADATA
qt_lottie-0.1.3.dist-info/WHEEL
qt_lottie-0.1.3.dist-info/top_level.txt
qt_lottie-0.1.3.dist-info/RECORD
