Metadata-Version: 2.4
Name: qt-lottie
Version: 0.1.3
Summary: Cross-platform Python library providing Lottie animation support for Qt applications
Author: Qt Lottie Contributors
Maintainer: Qt Lottie Contributors
License: MIT License
Project-URL: Homepage, https://gitlab.com/acemetrics-oss/qt-lottie
Project-URL: Repository, https://gitlab.com/acemetrics-oss/qt-lottie.git
Project-URL: Bug Tracker, https://gitlab.com/acemetrics-oss/qt-lottie/-/issues
Project-URL: Source Code, https://gitlab.com/acemetrics-oss/qt-lottie
Keywords: qt,lottie,animation,qml,pyside6,pyqt6,graphics
Classifier: Development Status :: 4 - Beta
Classifier: Intended Audience :: Developers
Classifier: Operating System :: OS Independent
Classifier: Programming Language :: Python :: 3
Classifier: Programming Language :: Python :: 3.8
Classifier: Programming Language :: Python :: 3.9
Classifier: Programming Language :: Python :: 3.10
Classifier: Programming Language :: Python :: 3.11
Classifier: Programming Language :: Python :: 3.12
Classifier: Topic :: Software Development :: Libraries :: Python Modules
Classifier: Topic :: Multimedia :: Graphics
Classifier: Topic :: Software Development :: User Interfaces
Requires-Python: >=3.8
Requires-Dist: rlottie-python>=1.0.0
Requires-Dist: Pillow>=8.0.0
Provides-Extra: pyside6
Requires-Dist: PySide6>=6.0.0; extra == "pyside6"
Provides-Extra: pyqt6
Requires-Dist: PyQt6>=6.0.0; extra == "pyqt6"
Provides-Extra: dev
Requires-Dist: pytest>=6.0; extra == "dev"
Requires-Dist: pytest-qt>=4.0; extra == "dev"
Requires-Dist: black>=22.0; extra == "dev"
Requires-Dist: flake8>=4.0; extra == "dev"
Requires-Dist: mypy>=0.900; extra == "dev"
Provides-Extra: docs
Requires-Dist: sphinx>=4.0; extra == "docs"
Requires-Dist: sphinx-rtd-theme>=1.0; extra == "docs"
